MANIFEST.in
README.md
optional_requirements_cassandra.txt
optional_requirements_extra_data_sources.txt
optional_requirements_scylla.txt
requirements.txt
requirements_test.txt
setup.py
mindsdb_datasources/__about__.py
mindsdb_datasources/__init__.py
mindsdb_datasources.egg-info/PKG-INFO
mindsdb_datasources.egg-info/SOURCES.txt
mindsdb_datasources.egg-info/dependency_links.txt
mindsdb_datasources.egg-info/requires.txt
mindsdb_datasources.egg-info/top_level.txt
mindsdb_datasources/datasources/__init__.py
mindsdb_datasources/datasources/aws_athena_ds.py
mindsdb_datasources/datasources/bigquery_ds.py
mindsdb_datasources/datasources/cassandra_ds.py
mindsdb_datasources/datasources/clickhouse_ds.py
mindsdb_datasources/datasources/crate_ds.py
mindsdb_datasources/datasources/data_source.py
mindsdb_datasources/datasources/dremio_ds.py
mindsdb_datasources/datasources/file_ds.py
mindsdb_datasources/datasources/gcs_ds.py
mindsdb_datasources/datasources/hive_ds.py
mindsdb_datasources/datasources/impala_ds.py
mindsdb_datasources/datasources/influx_ds.py
mindsdb_datasources/datasources/maria_ds.py
mindsdb_datasources/datasources/mongodb_ds.py
mindsdb_datasources/datasources/ms_sql_ds.py
mindsdb_datasources/datasources/mysql_ds.py
mindsdb_datasources/datasources/oracle_ds.py
mindsdb_datasources/datasources/phoenix_ds.py
mindsdb_datasources/datasources/postgres_ds.py
mindsdb_datasources/datasources/presto_ds.py
mindsdb_datasources/datasources/quest_ds.py
mindsdb_datasources/datasources/redshift_ds.py
mindsdb_datasources/datasources/s3_ds.py
mindsdb_datasources/datasources/scylla_ds.py
mindsdb_datasources/datasources/snowflake_ds.py
mindsdb_datasources/datasources/solr_ds.py
mindsdb_datasources/datasources/sqlite3_ds.py
mindsdb_datasources/datasources/timescale_ds.py
mindsdb_datasources/datasources/trino_ds.py
mindsdb_datasources/utilities/__init__.py
mindsdb_datasources/utilities/sql.py
mindsdb_datasources/utilities/ssl.py
tests/__init__.py
tests/common.py
tests/test_bigquery_ds.py
tests/test_clickhouse_ds.py
tests/test_dremio_ds.py
tests/test_file_ds.py
tests/test_hive.py
tests/test_impala_ds.py
tests/test_maria_ds.py
tests/test_mongodb_ds.py
tests/test_ms_sql_ds.py
tests/test_mysql_ds.py
