Metadata-Version: 2.1
Name: mindsdb-datasources
Version: 1.8.1
Summary: Datasources for mindsdb
Home-page: https://github.com/mindsdb/datasources
Author: MindsDB Inc
Author-email: jorge@mindsdb.com
License: GPL-3.0
Download-URL: https://pypi.org/project/mindsdb_datasources
Platform: UNKNOWN
Classifier: Programming Language :: Python :: 3
Classifier: License :: OSI Approved :: MIT License
Classifier: Operating System :: OS Independent
Requires-Python: >=3.6
Provides-Extra: extra_data_sources
Provides-Extra: scylla
Provides-Extra: cassandra
